<document xml:lang="fin" id="no_id"><header><title>Presidentti ja valtioneuvosto johtavat ulkopolitiikkaa - 
	Oikeusministeriö
</title><genre code="admin"/><author><unknown/></author><year>2016</year><wordcount>68</wordcount><conversion_status type="standard"/><availability><license type="standard"/></availability><multilingual/><origFileName>http://www.oikeusministerio.fi/fi/index/julkaisut/esitteet/perustuslaki/presidenttijavaltioneuvostojohtavatulkopolitiikkaa.html</origFileName><parallel_text xml:lang="eng" location="presidenttijavaltioneuvostojohtavatulkopolitiikkaa.html"/><parallel_text xml:lang="sme" location="presideantajastahtara273273ijo273ihitolgoriikkapolitihka.html"/><metadata><uncomplete/></metadata><version>XSLtemplate $Revision: 150288 $; file-specific xsl  Revision; common.xsl  $Revision$; </version></header><body><p type="title">Perustuslaki</p>
<p type="title">Presidentti ja valtioneuvosto johtavat ulkopolitiikkaa</p>
<p xml:lang="vep">8 LUKU</p>
<p>Suomen ulkopolitiikkaa johtaa tasavallan presidentti yhteistoiminnassa valtioneuvoston kanssa. Presidentti ja ulkosuhteista vastaavat ministerit keskustelevat merkittävimmistä päätöksistä hallituksen ulko- ja turvallisuuspoliittisessa valiokunnassa.</p>
<p>Eduskunta hyväksyy tärkeimmät kansainväliset sopimukset. Suomi liittyi Euroopan unionin jäseneksi vuonna 1995. Valtioneuvosto johtaa valmistautumista unionin päätöksentekoon ja huolehtii unionissa tehtyjen päätösten toimeenpanosta.</p>
<p>Valtioneuvoston on annettava eduskunnalle tietoa unionissa käsiteltävistä asioista. Eduskunta voi antaa unionin kokouksiin osallistuville ministereille toimintaohjeita.</p>
</body></document>
