<document xml:lang="fin" id="no_id"><header><title>Taitavia saamelaisnuoria kokoontui utsjoelle</title><genre code="admin"/><author><unknown/></author><year>unknown</year><wordcount>8</wordcount><conversion_status type="standard"/><availability><free/></availability><multilingual/><origFileName>http://www.samediggi.fi/index.php?option=com_docman&amp;task=doc_download&amp;gid=37&amp;Itemid=10</origFileName><parallel_text xml:lang="sme" location="saminuoraid_daiddadahpahus.pdf"/><metadata><uncomplete/></metadata><version>XSLtemplate $Revision: 139793 $; file-specific xsl  Revision; common.xsl  $Revision: 154948 $; </version></header><body><p><em type="bold">DAVVIN – TAVVEEN – TÂ´VVEN; </em>Kertomus elämästä pohjoisessa </p>
</body></document>